mcp_weather_http/__init__.py
mcp_weather_http/__main__.py
mcp_weather_http/server.py
zhujiaying_boss_mcp_weather_http-0.1.0.dist-info/METADATA
zhujiaying_boss_mcp_weather_http-0.1.0.dist-info/WHEEL
zhujiaying_boss_mcp_weather_http-0.1.0.dist-info/entry_points.txt
zhujiaying_boss_mcp_weather_http-0.1.0.dist-info/top_level.txt
zhujiaying_boss_mcp_weather_http-0.1.0.dist-info/RECORD
