Metadata-Version: 2.4
Name: zhujiaying-boss-mcp-weather-http
Version: 0.1.0
Summary: 输⼊OpenWeather-API-KEY，获取天⽓信息。
Requires-Python: >=3.10
Requires-Dist: httpx>=0.28.1
Requires-Dist: mcp>=1.9.4
